Metadata-Version: 1.1
Name: haystack-bio
Version: 0.4.0
Summary: Epigenetic Variability and Transcription Factor Motifs Analysis Pipeline
Home-page: http://github.com/lucapinello/Haystack
Author: Luca Pinello
Author-email: lpinello@jimmy.harvard.edu
License: UNKNOWN
Platform: UNKNOWN
Classifier: Development Status :: 4 - Beta
Classifier: Environment :: Console
Classifier: Intended Audience :: Developers
Classifier: Intended Audience :: Science/Research
Classifier: License :: OSI Approved :: BSD License
Classifier: Operating System :: MacOS :: MacOS X
Classifier: Operating System :: POSIX
Classifier: Topic :: Scientific/Engineering :: Bio-Informatics
Classifier: Programming Language :: Python
